{
  "version": "1.0.2",
  "description": "Snap for cabal.xyz",
  "proposedName": "cabal-xyz-snap",
  "repository": {
    "type": "git",
    "url": "git@github.com:0xPARC/cabal.git"
  },
  "source": {
    "shasum": "z1zHTBPcvzqHdxCjUaI6HT6ZyhNQuDpmbw8WL4zqHSo=",
    "location": {
      "npm": {
        "filePath": "dist/bundle.js",
        "packageName": "cabal-xyz-snap",
        "registry": "https://registry.npmjs.org"
      }
    }
  },
  "initialPermissions": {
    "snap_confirm": {},
    "snap_getBip44Entropy_60": {},
    "snap_manageState": {},
    "endowment:network-access": {}
  },
  "manifestVersion": "0.1"
}
